[
  {
    "id": "stellar",
    "symbol": "xlm",
    "name": "Stellar",
    "image": "https://coin-images.coingecko.com/coins/images/100/large/fmpFRHHQ_400x400.jpg?1735231350",
    "current_price": 0.24764,
    "market_cap": 8322590002,
    "market_cap_rank": 17,
    "fully_diluted_valuation": 12381801416,
    "total_volume": 2030758668,
    "high_24h": 0.295364,
    "low_24h": 0.217662,
    "price_change_24h": 0.02915584,
    "price_change_percentage_24h": 13.3446,
    "market_cap_change_24h": 980148325,
    "market_cap_change_percentage_24h": 13.34908,
    "circulating_supply": 33609355963.31727,
    "total_supply": 50001786839.91258,
    "max_supply": null,
    "ath": 0.875563,
    "ath_change_percentage": -71.73022,
    "ath_date": "2018-01-03T00:00:00.000Z",
    "atl": 0.00047612,
    "atl_change_percentage": 51886.45918,
    "atl_date": "2015-03-05T00:00:00.000Z",
    "roi": null,
    "last_updated": "2026-05-30T18:41:32.107Z",
    "price_change_percentage_24h_in_currency": 13.344599235873122
  },
  {
    "id": "binancecoin",
    "symbol": "bnb",
    "name": "BNB",
    "image": "https://coin-images.coingecko.com/coins/images/825/large/bnb-icon2_2x.png?1696501970",
    "current_price": 710.66,
    "market_cap": 95790240723,
    "market_cap_rank": 4,
    "fully_diluted_valuation": 95790239685,
    "total_volume": 2089966703,
    "high_24h": 713.19,
    "low_24h": 638.63,
    "price_change_24h": 69.15,
    "price_change_percentage_24h": 10.77969,
    "market_cap_change_24h": 9341931451,
    "market_cap_change_percentage_24h": 10.80638,
    "circulating_supply": 134784614.36,
    "total_supply": 134784612.9,
    "max_supply": 200000000.0,
    "ath": 1369.99,
    "ath_change_percentage": -48.1267,
    "ath_date": "2025-10-13T08:41:24.131Z",
    "atl": 0.0398177,
    "atl_change_percentage": 1784683.92278,
    "atl_date": "2017-10-19T00:00:00.000Z",
    "roi": null,
    "last_updated": "2026-05-30T18:41:32.096Z",
    "price_change_percentage_24h_in_currency": 10.779690059149146
  },
  {
    "id": "hedera-hashgraph",
    "symbol": "hbar",
    "name": "Hedera",
    "image": "https://coin-images.coingecko.com/coins/images/3688/large/hbar.png?1696504364",
    "current_price": 0.097875,
    "market_cap": 4245927886,
    "market_cap_rank": 27,
    "fully_diluted_valuation": 4894608671,
    "total_volume": 494576677,
    "high_24h": 0.109074,
    "low_24h": 0.090761,
    "price_change_24h": 0.00642291,
    "price_change_percentage_24h": 7.02325,
    "market_cap_change_24h": 280604428,
    "market_cap_change_percentage_24h": 7.07646,
    "circulating_supply": 43373517389.90581,
    "total_supply": 50000000000.0,
    "max_supply": 50000000000.0,
    "ath": 0.569229,
    "ath_change_percentage": -82.80259,
    "ath_date": "2021-09-15T10:40:28.318Z",
    "atl": 0.00986111,
    "atl_change_percentage": 892.71419,
    "atl_date": "2020-01-02T17:30:24.852Z",
    "roi": null,
    "last_updated": "2026-05-30T18:41:26.425Z",
    "price_change_percentage_24h_in_currency": 7.023248921068256
  },
  {
    "id": "the-open-network",
    "symbol": "ton",
    "name": "Toncoin",
    "image": "https://coin-images.coingecko.com/coins/images/17980/large/photo_2024-09-10_17.09.00.jpeg?1725963446",
    "current_price": 1.85,
    "market_cap": 4989676323,
    "market_cap_rank": 23,
    "fully_diluted_valuation": 9578072509,
    "total_volume": 142867211,
    "high_24h": 1.85,
    "low_24h": 1.73,
    "price_change_24h": 0.064586,
    "price_change_percentage_24h": 3.62591,
    "market_cap_change_24h": 192104511,
    "market_cap_change_percentage_24h": 4.0042,
    "circulating_supply": 2703069817.423605,
    "total_supply": 5188753143.84598,
    "max_supply": null,
    "ath": 8.25,
    "ath_change_percentage": -77.63427,
    "ath_date": "2024-06-15T00:36:51.509Z",
    "atl": 0.519364,
    "atl_change_percentage": 255.43088,
    "atl_date": "2021-09-21T00:33:11.092Z",
    "roi": null,
    "last_updated": "2026-05-30T18:41:24.792Z",
    "price_change_percentage_24h_in_currency": 3.6259123451156277
  },
  {
    "id": "hyperliquid",
    "symbol": "hype",
    "name": "Hyperliquid",
    "image": "https://coin-images.coingecko.com/coins/images/50882/large/hyperliquid.jpg?1729431300",
    "current_price": 68.16,
    "market_cap": 15157524989,
    "market_cap_rank": 11,
    "fully_diluted_valuation": 65094942329,
    "total_volume": 1215665729,
    "high_24h": 68.37,
    "low_24h": 64.05,
    "price_change_24h": 2.15,
    "price_change_percentage_24h": 3.25424,
    "market_cap_change_24h": 479124017,
    "market_cap_change_percentage_24h": 3.26414,
    "circulating_supply": 222445714.0741414,
    "total_supply": 955307079.4341414,
    "max_supply": 1000000000.0,
    "ath": 68.45,
    "ath_change_percentage": -0.42714,
    "ath_date": "2026-05-30T13:03:28.405Z",
    "atl": 3.81,
    "atl_change_percentage": 1689.44606,
    "atl_date": "2024-11-29T09:30:30.871Z",
    "roi": null,
    "last_updated": "2026-05-30T18:41:26.851Z",
    "price_change_percentage_24h_in_currency": 3.254242600807047
  },
  {
    "id": "chainlink",
    "symbol": "link",
    "name": "Chainlink",
    "image": "https://coin-images.coingecko.com/coins/images/877/large/Chainlink_Logo_500.png?1760023405",
    "current_price": 9.23,
    "market_cap": 6704525333,
    "market_cap_rank": 19,
    "fully_diluted_valuation": 9220912675,
    "total_volume": 255767489,
    "high_24h": 9.29,
    "low_24h": 8.93,
    "price_change_24h": 0.205564,
    "price_change_percentage_24h": 2.27881,
    "market_cap_change_24h": 146755242,
    "market_cap_change_percentage_24h": 2.23788,
    "circulating_supply": 727099970.4255477,
    "total_supply": 1000000000.0,
    "max_supply": 1000000000.0,
    "ath": 52.7,
    "ath_change_percentage": -82.49173,
    "ath_date": "2021-05-10T00:13:57.214Z",
    "atl": 0.148183,
    "atl_change_percentage": 6126.25623,
    "atl_date": "2017-11-29T00:00:00.000Z",
    "roi": null,
    "last_updated": "2026-05-30T18:41:31.155Z",
    "price_change_percentage_24h_in_currency": 2.2788114815781766
  },
  {
    "id": "shiba-inu",
    "symbol": "shib",
    "name": "Shiba Inu",
    "image": "https://coin-images.coingecko.com/coins/images/11939/large/shiba.png?1696511800",
    "current_price": 5.53e-06,
    "market_cap": 3257322837,
    "market_cap_rank": 32,
    "fully_diluted_valuation": 3258741467,
    "total_volume": 59037245,
    "high_24h": 5.54e-06,
    "low_24h": 5.37e-06,
    "price_change_24h": 1.03705e-07,
    "price_change_percentage_24h": 1.91108,
    "market_cap_change_24h": 61500636,
    "market_cap_change_percentage_24h": 1.92441,
    "circulating_supply": 589243247589820.5,
    "total_supply": 589499875004538.4,
    "max_supply": null,
    "ath": 8.616e-05,
    "ath_change_percentage": -93.58139,
    "ath_date": "2021-10-28T03:54:55.568Z",
    "atl": 5.6366e-11,
    "atl_change_percentage": 9811066.9961,
    "atl_date": "2020-11-28T11:26:25.838Z",
    "roi": null,
    "last_updated": "2026-05-30T18:41:25.602Z",
    "price_change_percentage_24h_in_currency": 1.911081249386546
  },
  {
    "id": "ripple",
    "symbol": "xrp",
    "name": "XRP",
    "image": "https://coin-images.coingecko.com/coins/images/44/large/xrp-symbol-white-128.png?1696501442",
    "current_price": 1.35,
    "market_cap": 83616885512,
    "market_cap_rank": 5,
    "fully_diluted_valuation": 134894806647,
    "total_volume": 1780724845,
    "high_24h": 1.36,
    "low_24h": 1.31,
    "price_change_24h": 0.02435147,
    "price_change_percentage_24h": 1.83789,
    "market_cap_change_24h": 1564533141,
    "market_cap_change_percentage_24h": 1.90675,
    "circulating_supply": 61977843307.0,
    "total_supply": 99985656462.0,
    "max_supply": 100000000000.0,
    "ath": 3.65,
    "ath_change_percentage": -62.99552,
    "ath_date": "2025-07-18T03:40:53.808Z",
    "atl": 0.00268621,
    "atl_change_percentage": 50131.55295,
    "atl_date": "2014-05-22T00:00:00.000Z",
    "roi": null,
    "last_updated": "2026-05-30T18:41:31.872Z",
    "price_change_percentage_24h_in_currency": 1.837885793100374
  },
  {
    "id": "cardano",
    "symbol": "ada",
    "name": "Cardano",
    "image": "https://coin-images.coingecko.com/coins/images/975/large/cardano.png?1696502090",
    "current_price": 0.236777,
    "market_cap": 8793294433,
    "market_cap_rank": 16,
    "fully_diluted_valuation": 10652598429,
    "total_volume": 356495900,
    "high_24h": 0.238506,
    "low_24h": 0.230895,
    "price_change_24h": 0.00417364,
    "price_change_percentage_24h": 1.79432,
    "market_cap_change_24h": 183597844,
    "market_cap_change_percentage_24h": 2.13245,
    "circulating_supply": 37145702256.21152,
    "total_supply": 45000000000.0,
    "max_supply": 45000000000.0,
    "ath": 3.09,
    "ath_change_percentage": -92.32964,
    "ath_date": "2021-09-02T06:00:10.474Z",
    "atl": 0.01925275,
    "atl_change_percentage": 1129.83567,
    "atl_date": "2020-03-13T02:22:55.044Z",
    "roi": null,
    "last_updated": "2026-05-30T18:41:29.520Z",
    "price_change_percentage_24h_in_currency": 1.7943159194181688
  },
  {
    "id": "monero",
    "symbol": "xmr",
    "name": "Monero",
    "image": "https://coin-images.coingecko.com/coins/images/69/large/monero_logo.png?1696501460",
    "current_price": 378.78,
    "market_cap": 7095163445,
    "market_cap_rank": 18,
    "fully_diluted_valuation": 7095169345,
    "total_volume": 267825555,
    "high_24h": 418.17,
    "low_24h": 365.14,
    "price_change_24h": 5.51,
    "price_change_percentage_24h": 1.47676,
    "market_cap_change_24h": 95389277,
    "market_cap_change_percentage_24h": 1.36275,
    "circulating_supply": 18758460.24947906,
    "total_supply": 18758475.84944041,
    "max_supply": null,
    "ath": 797.73,
    "ath_change_percentage": -52.51829,
    "ath_date": "2026-01-14T19:34:07.049Z",
    "atl": 0.216177,
    "atl_change_percentage": 175116.94486,
    "atl_date": "2015-01-14T00:00:00.000Z",
    "roi": null,
    "last_updated": "2026-05-30T18:41:28.594Z",
    "price_change_percentage_24h_in_currency": 1.476758712087317
  }
]