[
  {
    "id": "near",
    "symbol": "near",
    "name": "NEAR Protocol",
    "image": "https://coin-images.coingecko.com/coins/images/10365/large/near.jpg?1696510367",
    "current_price": 2.37,
    "market_cap": 3080247283,
    "market_cap_rank": 33,
    "fully_diluted_valuation": 3080247325,
    "total_volume": 805838350,
    "high_24h": 2.61,
    "low_24h": 2.36,
    "price_change_24h": -0.14260023405824906,
    "price_change_percentage_24h": -5.66979,
    "market_cap_change_24h": -200008825.66649628,
    "market_cap_change_percentage_24h": -6.09735,
    "circulating_supply": 1296829244.0,
    "total_supply": 1296829262.0,
    "max_supply": null,
    "ath": 20.44,
    "ath_change_percentage": -88.33787,
    "ath_date": "2022-01-16T22:09:45.873Z",
    "atl": 0.526762,
    "atl_change_percentage": 352.48498,
    "atl_date": "2020-11-04T16:09:15.137Z",
    "roi": null,
    "last_updated": "2026-05-30T02:24:43.756Z",
    "price_change_percentage_24h_in_currency": -5.6697866560826675
  },
  {
    "id": "bittensor",
    "symbol": "tao",
    "name": "Bittensor",
    "image": "https://coin-images.coingecko.com/coins/images/28452/large/ARUsPeNQ_400x400.jpeg?1696527447",
    "current_price": 252.26,
    "market_cap": 2424229711,
    "market_cap_rank": 40,
    "fully_diluted_valuation": 5304388817,
    "total_volume": 212177017,
    "high_24h": 260.44,
    "low_24h": 246.86,
    "price_change_24h": -7.052248569924586,
    "price_change_percentage_24h": -2.7196,
    "market_cap_change_24h": -68811664.20770264,
    "market_cap_change_percentage_24h": -2.76015,
    "circulating_supply": 9597491.0,
    "total_supply": 21000000.0,
    "max_supply": 21000000.0,
    "ath": 757.6,
    "ath_change_percentage": -66.60025,
    "ath_date": "2024-03-07T18:45:36.466Z",
    "atl": 30.83,
    "atl_change_percentage": 720.75387,
    "atl_date": "2023-05-14T08:57:53.732Z",
    "roi": null,
    "last_updated": "2026-05-30T02:24:45.899Z",
    "price_change_percentage_24h_in_currency": -2.719598955841888
  },
  {
    "id": "memecore",
    "symbol": "m",
    "name": "MemeCore",
    "image": "https://coin-images.coingecko.com/coins/images/53247/large/square-bg-transparent.png?1752637478",
    "current_price": 2.93,
    "market_cap": 3865288600,
    "market_cap_rank": 30,
    "fully_diluted_valuation": 15894049695,
    "total_volume": 7523108,
    "high_24h": 3.2,
    "low_24h": 2.95,
    "price_change_24h": -0.06039391363675284,
    "price_change_percentage_24h": -2.01952,
    "market_cap_change_24h": -46891885.4436326,
    "market_cap_change_percentage_24h": -1.19861,
    "circulating_supply": 1306975292.659392,
    "total_supply": 5374276645.304309,
    "max_supply": 10000000000.0,
    "ath": 4.82,
    "ath_change_percentage": -38.66716,
    "ath_date": "2026-04-24T01:10:07.284Z",
    "atl": 0.04746135,
    "atl_change_percentage": 6125.95818,
    "atl_date": "2025-07-04T03:56:17.448Z",
    "roi": null,
    "last_updated": "2026-05-30T02:24:45.126Z",
    "price_change_percentage_24h_in_currency": -2.019522443314052
  },
  {
    "id": "tron",
    "symbol": "trx",
    "name": "TRON",
    "image": "https://coin-images.coingecko.com/coins/images/1094/large/photo_2026-04-13_09-59-16.png?1776048311",
    "current_price": 0.344694,
    "market_cap": 32681984957,
    "market_cap_rank": 8,
    "fully_diluted_valuation": 32682166990,
    "total_volume": 707375916,
    "high_24h": 0.351525,
    "low_24h": 0.34134,
    "price_change_24h": -0.006618386737080317,
    "price_change_percentage_24h": -1.88391,
    "market_cap_change_24h": -627607471.8487396,
    "market_cap_change_percentage_24h": -1.88416,
    "circulating_supply": 94812553398.29669,
    "total_supply": 94813081487.44429,
    "max_supply": null,
    "ath": 0.431288,
    "ath_change_percentage": -20.07817,
    "ath_date": "2024-12-04T00:10:40.323Z",
    "atl": 0.00180434,
    "atl_change_percentage": 19003.56294,
    "atl_date": "2017-11-12T00:00:00.000Z",
    "roi": {
      "times": 180.41765255105958,
      "currency": "usd",
      "percentage": 18041.76525510596
    },
    "last_updated": "2026-05-30T02:24:42.361Z",
    "price_change_percentage_24h_in_currency": -1.8839060778359527
  },
  {
    "id": "zcash",
    "symbol": "zec",
    "name": "Zcash",
    "image": "https://coin-images.coingecko.com/coins/images/486/large/circle-zcash-color.png?1696501740",
    "current_price": 535.54,
    "market_cap": 8938174704,
    "market_cap_rank": 16,
    "fully_diluted_valuation": 8938174704,
    "total_volume": 601856340,
    "high_24h": 554.95,
    "low_24h": 525.61,
    "price_change_24h": -9.64375643801418,
    "price_change_percentage_24h": -1.7689,
    "market_cap_change_24h": -160575096.04681587,
    "market_cap_change_percentage_24h": -1.7648,
    "circulating_supply": 16688225.1655448,
    "total_supply": 16688225.1655448,
    "max_supply": 21000000.0,
    "ath": 3191.93,
    "ath_change_percentage": -83.22204,
    "ath_date": "2016-10-29T00:00:00.000Z",
    "atl": 16.08,
    "atl_change_percentage": 3230.45018,
    "atl_date": "2024-07-05T04:22:29.321Z",
    "roi": null,
    "last_updated": "2026-05-30T02:24:45.109Z",
    "price_change_percentage_24h_in_currency": -1.7688974960998576
  },
  {
    "id": "sui",
    "symbol": "sui",
    "name": "Sui",
    "image": "https://coin-images.coingecko.com/coins/images/26375/large/sui-ocean-square.png?1727791290",
    "current_price": 0.913443,
    "market_cap": 3660304027,
    "market_cap_rank": 31,
    "fully_diluted_valuation": 9138381285,
    "total_volume": 597537319,
    "high_24h": 0.930584,
    "low_24h": 0.893879,
    "price_change_24h": -0.013102740839511573,
    "price_change_percentage_24h": -1.41415,
    "market_cap_change_24h": -57802640.711354256,
    "market_cap_change_percentage_24h": -1.55463,
    "circulating_supply": 4005418369.566699,
    "total_supply": 10000000000.0,
    "max_supply": 10000000000.0,
    "ath": 5.35,
    "ath_change_percentage": -82.91534,
    "ath_date": "2025-01-04T22:56:18.063Z",
    "atl": 0.364846,
    "atl_change_percentage": 150.36368,
    "atl_date": "2023-10-19T10:40:30.078Z",
    "roi": null,
    "last_updated": "2026-05-30T02:24:43.743Z",
    "price_change_percentage_24h_in_currency": -1.4141499048210255
  },
  {
    "id": "the-open-network",
    "symbol": "ton",
    "name": "Toncoin",
    "image": "https://coin-images.coingecko.com/coins/images/17980/large/photo_2024-09-10_17.09.00.jpeg?1725963446",
    "current_price": 1.76,
    "market_cap": 4768395630,
    "market_cap_rank": 23,
    "fully_diluted_valuation": 9153910192,
    "total_volume": 163518828,
    "high_24h": 1.8,
    "low_24h": 1.71,
    "price_change_24h": -0.005389007047493344,
    "price_change_percentage_24h": -0.30467,
    "market_cap_change_24h": -18294505.410190582,
    "market_cap_change_percentage_24h": -0.3822,
    "circulating_supply": 2702683118.391752,
    "total_supply": 5188352742.062756,
    "max_supply": null,
    "ath": 8.25,
    "ath_change_percentage": -78.60852,
    "ath_date": "2024-06-15T00:36:51.509Z",
    "atl": 0.519364,
    "atl_change_percentage": 239.94837,
    "atl_date": "2021-09-21T00:33:11.092Z",
    "roi": null,
    "last_updated": "2026-05-30T02:24:43.208Z",
    "price_change_percentage_24h_in_currency": -0.3046675777354829
  },
  {
    "id": "dai",
    "symbol": "dai",
    "name": "Dai",
    "image": "https://coin-images.coingecko.com/coins/images/9956/large/Badge_Dai.png?1696509996",
    "current_price": 0.999507,
    "market_cap": 4370801378,
    "market_cap_rank": 27,
    "fully_diluted_valuation": 4370801378,
    "total_volume": 171512308,
    "high_24h": 0.999733,
    "low_24h": 0.999184,
    "price_change_24h": -8.2398697465402e-05,
    "price_change_percentage_24h": -0.00824,
    "market_cap_change_24h": 16808901,
    "market_cap_change_percentage_24h": 0.38606,
    "circulating_supply": 4373303740.536381,
    "total_supply": 4373303740.536381,
    "max_supply": null,
    "ath": 1.22,
    "ath_change_percentage": -17.99914,
    "ath_date": "2020-03-13T03:02:50.373Z",
    "atl": 0.88196,
    "atl_change_percentage": 13.33095,
    "atl_date": "2023-03-11T07:50:50.514Z",
    "roi": null,
    "last_updated": "2026-05-30T02:24:47.222Z",
    "price_change_percentage_24h_in_currency": -0.008243253279216298
  },
  {
    "id": "global-dollar",
    "symbol": "usdg",
    "name": "Global Dollar",
    "image": "https://coin-images.coingecko.com/coins/images/51281/large/GDN_USDG_Token_200x200.png?1730484111",
    "current_price": 0.999715,
    "market_cap": 2618162891,
    "market_cap_rank": 38,
    "fully_diluted_valuation": 2618162891,
    "total_volume": 71688494,
    "high_24h": 0.999969,
    "low_24h": 0.999461,
    "price_change_24h": -5.8811390694857e-05,
    "price_change_percentage_24h": -0.00588,
    "market_cap_change_24h": -16031510.27508688,
    "market_cap_change_percentage_24h": -0.60859,
    "circulating_supply": 2618800270.133224,
    "total_supply": 2618800270.133224,
    "max_supply": null,
    "ath": 1.65,
    "ath_change_percentage": -39.57315,
    "ath_date": "2025-01-30T00:11:05.728Z",
    "atl": 0.907561,
    "atl_change_percentage": 10.16026,
    "atl_date": "2024-11-11T23:55:50.604Z",
    "roi": null,
    "last_updated": "2026-05-30T02:24:45.118Z",
    "price_change_percentage_24h_in_currency": -0.005882469695679814
  },
  {
    "id": "usds",
    "symbol": "usds",
    "name": "USDS",
    "image": "https://coin-images.coingecko.com/coins/images/39926/large/usds.webp?1726666683",
    "current_price": 0.999533,
    "market_cap": 11050825448,
    "market_cap_rank": 12,
    "fully_diluted_valuation": 11050825448,
    "total_volume": 97331857,
    "high_24h": 0.999753,
    "low_24h": 0.99927,
    "price_change_24h": -4.1910918756494e-05,
    "price_change_percentage_24h": -0.00419,
    "market_cap_change_24h": -27389648.509986877,
    "market_cap_change_percentage_24h": -0.24724,
    "circulating_supply": 11056170543.66228,
    "total_supply": 11056170543.66228,
    "max_supply": null,
    "ath": 1.15,
    "ath_change_percentage": -13.24311,
    "ath_date": "2026-04-02T07:21:14.655Z",
    "atl": 0.948265,
    "atl_change_percentage": 5.40473,
    "atl_date": "2024-10-03T13:19:28.826Z",
    "roi": null,
    "last_updated": "2026-05-30T02:24:44.723Z",
    "price_change_percentage_24h_in_currency": -0.004192873326312615
  }
]