[
  {
    "id": "zcash",
    "symbol": "zec",
    "name": "Zcash",
    "image": "https://coin-images.coingecko.com/coins/images/486/large/circle-zcash-color.png?1696501740",
    "current_price": 525.27,
    "market_cap": 8770665692,
    "market_cap_rank": 15,
    "fully_diluted_valuation": 8770665692,
    "total_volume": 748810494,
    "high_24h": 579.09,
    "low_24h": 522.9,
    "price_change_24h": -47.239423831981185,
    "price_change_percentage_24h": -8.25135,
    "market_cap_change_24h": -783431613.8750896,
    "market_cap_change_percentage_24h": -8.19995,
    "circulating_supply": 16688225.1655448,
    "total_supply": 16688225.1655448,
    "max_supply": 21000000.0,
    "ath": 3191.93,
    "ath_change_percentage": -83.54394,
    "ath_date": "2016-10-29T00:00:00.000Z",
    "atl": 16.08,
    "atl_change_percentage": 3166.55175,
    "atl_date": "2024-07-05T04:22:29.321Z",
    "roi": null,
    "last_updated": "2026-05-28T07:29:26.706Z",
    "price_change_percentage_24h_in_currency": -8.251351397950515
  },
  {
    "id": "sui",
    "symbol": "sui",
    "name": "Sui",
    "image": "https://coin-images.coingecko.com/coins/images/26375/large/sui-ocean-square.png?1727791290",
    "current_price": 0.922512,
    "market_cap": 3697684194,
    "market_cap_rank": 30,
    "fully_diluted_valuation": 9231705287,
    "total_volume": 761838871,
    "high_24h": 1.01,
    "low_24h": 0.909238,
    "price_change_24h": -0.080060228175869,
    "price_change_percentage_24h": -7.98549,
    "market_cap_change_24h": -317120681.56304264,
    "market_cap_change_percentage_24h": -7.89878,
    "circulating_supply": 4005418369.566699,
    "total_supply": 10000000000.0,
    "max_supply": 10000000000.0,
    "ath": 5.35,
    "ath_change_percentage": -82.74572,
    "ath_date": "2025-01-04T22:56:18.063Z",
    "atl": 0.364846,
    "atl_change_percentage": 152.84935,
    "atl_date": "2023-10-19T10:40:30.078Z",
    "roi": null,
    "last_updated": "2026-05-28T07:29:25.366Z",
    "price_change_percentage_24h_in_currency": -7.985486169688248
  },
  {
    "id": "hyperliquid",
    "symbol": "hype",
    "name": "Hyperliquid",
    "image": "https://coin-images.coingecko.com/coins/images/50882/large/hyperliquid.jpg?1729431300",
    "current_price": 57.9,
    "market_cap": 12879167760,
    "market_cap_rank": 11,
    "fully_diluted_valuation": 55310394220,
    "total_volume": 955667952,
    "high_24h": 63.18,
    "low_24h": 56.78,
    "price_change_24h": -4.609364271887536,
    "price_change_percentage_24h": -7.37446,
    "market_cap_change_24h": -1015410664.6702652,
    "market_cap_change_percentage_24h": -7.30796,
    "circulating_supply": 222445714.0741414,
    "total_supply": 955307079.4341414,
    "max_supply": 1000000000.0,
    "ath": 64.44,
    "ath_change_percentage": -10.16221,
    "ath_date": "2026-05-26T14:28:48.405Z",
    "atl": 3.81,
    "atl_change_percentage": 1420.05809,
    "atl_date": "2024-11-29T09:30:30.871Z",
    "roi": null,
    "last_updated": "2026-05-28T07:29:27.034Z",
    "price_change_percentage_24h_in_currency": -7.374461841427565
  },
  {
    "id": "chainlink",
    "symbol": "link",
    "name": "Chainlink",
    "image": "https://coin-images.coingecko.com/coins/images/877/large/Chainlink_Logo_500.png?1760023405",
    "current_price": 8.87,
    "market_cap": 6449973526,
    "market_cap_rank": 19,
    "fully_diluted_valuation": 8870820779,
    "total_volume": 357208512,
    "high_24h": 9.44,
    "low_24h": 8.79,
    "price_change_24h": -0.546976094701936,
    "price_change_percentage_24h": -5.80924,
    "market_cap_change_24h": -396128258.52548885,
    "market_cap_change_percentage_24h": -5.78619,
    "circulating_supply": 727099970.4255477,
    "total_supply": 1000000000.0,
    "max_supply": 1000000000.0,
    "ath": 52.7,
    "ath_change_percentage": -83.17029,
    "ath_date": "2021-05-10T00:13:57.214Z",
    "atl": 0.148183,
    "atl_change_percentage": 5884.94707,
    "atl_date": "2017-11-29T00:00:00.000Z",
    "roi": null,
    "last_updated": "2026-05-28T07:29:29.258Z",
    "price_change_percentage_24h_in_currency": -5.809237355860467
  },
  {
    "id": "bittensor",
    "symbol": "tao",
    "name": "Bittensor",
    "image": "https://coin-images.coingecko.com/coins/images/28452/large/ARUsPeNQ_400x400.jpeg?1696527447",
    "current_price": 259.45,
    "market_cap": 2491448341,
    "market_cap_rank": 39,
    "fully_diluted_valuation": 5451468010,
    "total_volume": 209285095,
    "high_24h": 280.21,
    "low_24h": 255.15,
    "price_change_24h": -14.852160053685225,
    "price_change_percentage_24h": -5.41449,
    "market_cap_change_24h": -141010478.0617075,
    "market_cap_change_percentage_24h": -5.35661,
    "circulating_supply": 9597491.0,
    "total_supply": 21000000.0,
    "max_supply": 21000000.0,
    "ath": 757.6,
    "ath_change_percentage": -65.82745,
    "ath_date": "2024-03-07T18:45:36.466Z",
    "atl": 30.83,
    "atl_change_percentage": 739.74429,
    "atl_date": "2023-05-14T08:57:53.732Z",
    "roi": null,
    "last_updated": "2026-05-28T07:29:25.456Z",
    "price_change_percentage_24h_in_currency": -5.414487287852387
  },
  {
    "id": "bitcoin-cash",
    "symbol": "bch",
    "name": "Bitcoin Cash",
    "image": "https://coin-images.coingecko.com/coins/images/780/large/bitcoin-cash-circle.png?1696501932",
    "current_price": 327.01,
    "market_cap": 6553568229,
    "market_cap_rank": 18,
    "fully_diluted_valuation": 6553570273,
    "total_volume": 182899525,
    "high_24h": 346.05,
    "low_24h": 325.09,
    "price_change_24h": -17.705913709678214,
    "price_change_percentage_24h": -5.13641,
    "market_cap_change_24h": -354351818.54420185,
    "market_cap_change_percentage_24h": -5.12965,
    "circulating_supply": 20040356.14665078,
    "total_supply": 20040362.39665078,
    "max_supply": 21000000.0,
    "ath": 3785.82,
    "ath_change_percentage": -91.3623,
    "ath_date": "2017-12-20T00:00:00.000Z",
    "atl": 76.93,
    "atl_change_percentage": 325.04534,
    "atl_date": "2018-12-16T00:00:00.000Z",
    "roi": null,
    "last_updated": "2026-05-28T07:29:29.065Z",
    "price_change_percentage_24h_in_currency": -5.136411806077508
  },
  {
    "id": "the-open-network",
    "symbol": "ton",
    "name": "Toncoin",
    "image": "https://coin-images.coingecko.com/coins/images/17980/large/photo_2024-09-10_17.09.00.jpeg?1725963446",
    "current_price": 1.8,
    "market_cap": 4858392707,
    "market_cap_rank": 23,
    "fully_diluted_valuation": 9328333073,
    "total_volume": 181282978,
    "high_24h": 1.91,
    "low_24h": 1.77,
    "price_change_24h": -0.08851970202275594,
    "price_change_percentage_24h": -4.6913,
    "market_cap_change_24h": -234861440.19564533,
    "market_cap_change_percentage_24h": -4.61123,
    "circulating_supply": 2701676221.074964,
    "total_supply": 5187340168.814378,
    "max_supply": null,
    "ath": 8.25,
    "ath_change_percentage": -78.26292,
    "ath_date": "2024-06-15T00:36:51.509Z",
    "atl": 0.519364,
    "atl_change_percentage": 245.44052,
    "atl_date": "2021-09-21T00:33:11.092Z",
    "roi": null,
    "last_updated": "2026-05-28T07:29:25.216Z",
    "price_change_percentage_24h_in_currency": -4.691303964102488
  },
  {
    "id": "near",
    "symbol": "near",
    "name": "NEAR Protocol",
    "image": "https://coin-images.coingecko.com/coins/images/10365/large/near.jpg?1696510367",
    "current_price": 2.39,
    "market_cap": 3104706043,
    "market_cap_rank": 34,
    "fully_diluted_valuation": 3104706067,
    "total_volume": 875613460,
    "high_24h": 2.7,
    "low_24h": 2.37,
    "price_change_24h": -0.11209548057493413,
    "price_change_percentage_24h": -4.47296,
    "market_cap_change_24h": -144246074.49369574,
    "market_cap_change_percentage_24h": -4.43977,
    "circulating_supply": 1296669623.0,
    "total_supply": 1296669633.0,
    "max_supply": null,
    "ath": 20.44,
    "ath_change_percentage": -88.34816,
    "ath_date": "2022-01-16T22:09:45.873Z",
    "atl": 0.526762,
    "atl_change_percentage": 352.08557,
    "atl_date": "2020-11-04T16:09:15.137Z",
    "roi": null,
    "last_updated": "2026-05-28T07:29:26.292Z",
    "price_change_percentage_24h_in_currency": -4.472958961500704
  },
  {
    "id": "ethereum",
    "symbol": "eth",
    "name": "Ethereum",
    "image": "https://coin-images.coingecko.com/coins/images/279/large/ethereum.png?1696501628",
    "current_price": 1986.48,
    "market_cap": 239754873918,
    "market_cap_rank": 2,
    "fully_diluted_valuation": 239754873918,
    "total_volume": 16868767345,
    "high_24h": 2091.68,
    "low_24h": 1970.91,
    "price_change_24h": -89.5457530971189,
    "price_change_percentage_24h": -4.31333,
    "market_cap_change_24h": -10759159243.021881,
    "market_cap_change_percentage_24h": -4.29483,
    "circulating_supply": 120685415.2818607,
    "total_supply": 120685415.2818607,
    "max_supply": null,
    "ath": 4946.05,
    "ath_change_percentage": -59.83703,
    "ath_date": "2025-08-24T19:21:03.333Z",
    "atl": 0.432979,
    "atl_change_percentage": 458693.76234,
    "atl_date": "2015-10-20T00:00:00.000Z",
    "roi": {
      "times": 35.31160667721792,
      "currency": "btc",
      "percentage": 3531.160667721792
    },
    "last_updated": "2026-05-28T07:29:31.904Z",
    "price_change_percentage_24h_in_currency": -4.313328219765271
  },
  {
    "id": "shiba-inu",
    "symbol": "shib",
    "name": "Shiba Inu",
    "image": "https://coin-images.coingecko.com/coins/images/11939/large/shiba.png?1696511800",
    "current_price": 5.29e-06,
    "market_cap": 3113714196,
    "market_cap_rank": 33,
    "fully_diluted_valuation": 3115070286,
    "total_volume": 169963395,
    "high_24h": 5.55e-06,
    "low_24h": 5.24e-06,
    "price_change_24h": -2.35046025428e-07,
    "price_change_percentage_24h": -4.25439,
    "market_cap_change_24h": -144586716.40638065,
    "market_cap_change_percentage_24h": -4.43749,
    "circulating_supply": 589243253266753.6,
    "total_supply": 589499881381471.5,
    "max_supply": null,
    "ath": 8.616e-05,
    "ath_change_percentage": -93.86047,
    "ath_date": "2021-10-28T03:54:55.568Z",
    "atl": 5.6366e-11,
    "atl_change_percentage": 9384466.80449,
    "atl_date": "2020-11-28T11:26:25.838Z",
    "roi": null,
    "last_updated": "2026-05-28T07:29:24.574Z",
    "price_change_percentage_24h_in_currency": -4.254388403645958
  }
]