[
  {
    "id": "hyperliquid",
    "symbol": "hype",
    "name": "Hyperliquid",
    "image": "https://coin-images.coingecko.com/coins/images/50882/large/hyperliquid.jpg?1729431300",
    "current_price": 56.79,
    "market_cap": 12623144118,
    "market_cap_rank": 11,
    "fully_diluted_valuation": 54210884623,
    "total_volume": 965178176,
    "high_24h": 63.18,
    "low_24h": 56.62,
    "price_change_24h": -5.5585157552574245,
    "price_change_percentage_24h": -8.91562,
    "market_cap_change_24h": -1201534928.3833942,
    "market_cap_change_percentage_24h": -8.69123,
    "circulating_supply": 222445714.0741414,
    "total_supply": 955307079.4341414,
    "max_supply": 1000000000.0,
    "ath": 64.44,
    "ath_change_percentage": -11.8811,
    "ath_date": "2026-05-26T14:28:48.405Z",
    "atl": 3.81,
    "atl_change_percentage": 1390.97438,
    "atl_date": "2024-11-29T09:30:30.871Z",
    "roi": null,
    "last_updated": "2026-05-28T09:15:46.342Z",
    "price_change_percentage_24h_in_currency": -8.915615490546907
  },
  {
    "id": "zcash",
    "symbol": "zec",
    "name": "Zcash",
    "image": "https://coin-images.coingecko.com/coins/images/486/large/circle-zcash-color.png?1696501740",
    "current_price": 522.07,
    "market_cap": 8712457093,
    "market_cap_rank": 15,
    "fully_diluted_valuation": 8712457093,
    "total_volume": 786976701,
    "high_24h": 579.09,
    "low_24h": 522.9,
    "price_change_24h": -49.81350689106637,
    "price_change_percentage_24h": -8.7104,
    "market_cap_change_24h": -825925153.9038448,
    "market_cap_change_percentage_24h": -8.65896,
    "circulating_supply": 16688225.1655448,
    "total_supply": 16688225.1655448,
    "max_supply": 21000000.0,
    "ath": 3191.93,
    "ath_change_percentage": -83.644,
    "ath_date": "2016-10-29T00:00:00.000Z",
    "atl": 16.08,
    "atl_change_percentage": 3146.69027,
    "atl_date": "2024-07-05T04:22:29.321Z",
    "roi": null,
    "last_updated": "2026-05-28T09:15:45.992Z",
    "price_change_percentage_24h_in_currency": -8.710396719324892
  },
  {
    "id": "sui",
    "symbol": "sui",
    "name": "Sui",
    "image": "https://coin-images.coingecko.com/coins/images/26375/large/sui-ocean-square.png?1727791290",
    "current_price": 0.918106,
    "market_cap": 3680826439,
    "market_cap_rank": 30,
    "fully_diluted_valuation": 9189617911,
    "total_volume": 762918126,
    "high_24h": 1.01,
    "low_24h": 0.909238,
    "price_change_24h": -0.07443087554723427,
    "price_change_percentage_24h": -7.49905,
    "market_cap_change_24h": -301889362.6952925,
    "market_cap_change_percentage_24h": -7.57999,
    "circulating_supply": 4005418369.566699,
    "total_supply": 10000000000.0,
    "max_supply": 10000000000.0,
    "ath": 5.35,
    "ath_change_percentage": -82.82812,
    "ath_date": "2025-01-04T22:56:18.063Z",
    "atl": 0.364846,
    "atl_change_percentage": 151.64194,
    "atl_date": "2023-10-19T10:40:30.078Z",
    "roi": null,
    "last_updated": "2026-05-28T09:15:44.437Z",
    "price_change_percentage_24h_in_currency": -7.499051255052448
  },
  {
    "id": "bitcoin-cash",
    "symbol": "bch",
    "name": "Bitcoin Cash",
    "image": "https://coin-images.coingecko.com/coins/images/780/large/bitcoin-cash-circle.png?1696501932",
    "current_price": 324.48,
    "market_cap": 6502586723,
    "market_cap_rank": 18,
    "fully_diluted_valuation": 6502677981,
    "total_volume": 207150574,
    "high_24h": 346.05,
    "low_24h": 324.12,
    "price_change_24h": -18.410392502062678,
    "price_change_percentage_24h": -5.3692,
    "market_cap_change_24h": -371653177.20059013,
    "market_cap_change_percentage_24h": -5.40646,
    "circulating_supply": 20040412.39665078,
    "total_supply": 20040693.64665078,
    "max_supply": 21000000.0,
    "ath": 3785.82,
    "ath_change_percentage": -91.42911,
    "ath_date": "2017-12-20T00:00:00.000Z",
    "atl": 76.93,
    "atl_change_percentage": 321.75763,
    "atl_date": "2018-12-16T00:00:00.000Z",
    "roi": null,
    "last_updated": "2026-05-28T09:15:49.832Z",
    "price_change_percentage_24h_in_currency": -5.369202741953523
  },
  {
    "id": "chainlink",
    "symbol": "link",
    "name": "Chainlink",
    "image": "https://coin-images.coingecko.com/coins/images/877/large/Chainlink_Logo_500.png?1760023405",
    "current_price": 8.85,
    "market_cap": 6437887177,
    "market_cap_rank": 19,
    "fully_diluted_valuation": 8854198101,
    "total_volume": 349479477,
    "high_24h": 9.44,
    "low_24h": 8.79,
    "price_change_24h": -0.4916407094662283,
    "price_change_percentage_24h": -5.26022,
    "market_cap_change_24h": -370213122.41019344,
    "market_cap_change_percentage_24h": -5.43783,
    "circulating_supply": 727099970.4255477,
    "total_supply": 1000000000.0,
    "max_supply": 1000000000.0,
    "ath": 52.7,
    "ath_change_percentage": -83.19666,
    "ath_date": "2021-05-10T00:13:57.214Z",
    "atl": 0.148183,
    "atl_change_percentage": 5875.56871,
    "atl_date": "2017-11-29T00:00:00.000Z",
    "roi": null,
    "last_updated": "2026-05-28T09:15:48.854Z",
    "price_change_percentage_24h_in_currency": -5.260218066905009
  },
  {
    "id": "bittensor",
    "symbol": "tao",
    "name": "Bittensor",
    "image": "https://coin-images.coingecko.com/coins/images/28452/large/ARUsPeNQ_400x400.jpeg?1696527447",
    "current_price": 261.08,
    "market_cap": 2506128725,
    "market_cap_rank": 39,
    "fully_diluted_valuation": 5483589746,
    "total_volume": 215792007,
    "high_24h": 280.21,
    "low_24h": 255.15,
    "price_change_24h": -12.87166309293832,
    "price_change_percentage_24h": -4.69856,
    "market_cap_change_24h": -124072916.7999978,
    "market_cap_change_percentage_24h": -4.71724,
    "circulating_supply": 9597491.0,
    "total_supply": 21000000.0,
    "max_supply": 21000000.0,
    "ath": 757.6,
    "ath_change_percentage": -65.60878,
    "ath_date": "2024-03-07T18:45:36.466Z",
    "atl": 30.83,
    "atl_change_percentage": 745.11779,
    "atl_date": "2023-05-14T08:57:53.732Z",
    "roi": null,
    "last_updated": "2026-05-28T09:15:44.225Z",
    "price_change_percentage_24h_in_currency": -4.69856211429677
  },
  {
    "id": "near",
    "symbol": "near",
    "name": "NEAR Protocol",
    "image": "https://coin-images.coingecko.com/coins/images/10365/large/near.jpg?1696510367",
    "current_price": 2.39,
    "market_cap": 3091079602,
    "market_cap_rank": 34,
    "fully_diluted_valuation": 3091079628,
    "total_volume": 824096138,
    "high_24h": 2.7,
    "low_24h": 2.37,
    "price_change_24h": -0.11675376174057783,
    "price_change_percentage_24h": -4.66556,
    "market_cap_change_24h": -180495577.29788446,
    "market_cap_change_percentage_24h": -5.51708,
    "circulating_supply": 1296696523.0,
    "total_supply": 1296696534.0,
    "max_supply": null,
    "ath": 20.44,
    "ath_change_percentage": -88.32518,
    "ath_date": "2022-01-16T22:09:45.873Z",
    "atl": 0.526762,
    "atl_change_percentage": 352.97713,
    "atl_date": "2020-11-04T16:09:15.137Z",
    "roi": null,
    "last_updated": "2026-05-28T09:15:42.999Z",
    "price_change_percentage_24h_in_currency": -4.665562531731003
  },
  {
    "id": "ethereum",
    "symbol": "eth",
    "name": "Ethereum",
    "image": "https://coin-images.coingecko.com/coins/images/279/large/ethereum.png?1696501628",
    "current_price": 1984.33,
    "market_cap": 239476344931,
    "market_cap_rank": 2,
    "fully_diluted_valuation": 239476344931,
    "total_volume": 17273760819,
    "high_24h": 2083.38,
    "low_24h": 1970.91,
    "price_change_24h": -93.16981800438612,
    "price_change_percentage_24h": -4.48471,
    "market_cap_change_24h": -11287503418.108673,
    "market_cap_change_percentage_24h": -4.50125,
    "circulating_supply": 120685415.2818607,
    "total_supply": 120685415.2818607,
    "max_supply": null,
    "ath": 4946.05,
    "ath_change_percentage": -59.88049,
    "ath_date": "2025-08-24T19:21:03.333Z",
    "atl": 0.432979,
    "atl_change_percentage": 458197.3172,
    "atl_date": "2015-10-20T00:00:00.000Z",
    "roi": {
      "times": 35.2506334317143,
      "currency": "btc",
      "percentage": 3525.0633431714296
    },
    "last_updated": "2026-05-28T09:15:59.600Z",
    "price_change_percentage_24h_in_currency": -4.484710344487647
  },
  {
    "id": "tron",
    "symbol": "trx",
    "name": "TRON",
    "image": "https://coin-images.coingecko.com/coins/images/1094/large/photo_2026-04-13_09-59-16.png?1776048311",
    "current_price": 0.356829,
    "market_cap": 33843305817,
    "market_cap_rank": 8,
    "fully_diluted_valuation": 33843306645,
    "total_volume": 729187816,
    "high_24h": 0.37386,
    "low_24h": 0.357181,
    "price_change_24h": -0.016218049755720165,
    "price_change_percentage_24h": -4.34745,
    "market_cap_change_24h": -1546087145.0645523,
    "market_cap_change_percentage_24h": -4.36879,
    "circulating_supply": 94811822842.3832,
    "total_supply": 94811825161.22859,
    "max_supply": null,
    "ath": 0.431288,
    "ath_change_percentage": -17.2643,
    "ath_date": "2024-12-04T00:10:40.323Z",
    "atl": 0.00180434,
    "atl_change_percentage": 19676.15608,
    "atl_date": "2017-11-12T00:00:00.000Z",
    "roi": {
      "times": 186.80495680181104,
      "currency": "usd",
      "percentage": 18680.495680181106
    },
    "last_updated": "2026-05-28T09:15:43.094Z",
    "price_change_percentage_24h_in_currency": -4.3474493625750785
  },
  {
    "id": "the-open-network",
    "symbol": "ton",
    "name": "Toncoin",
    "image": "https://coin-images.coingecko.com/coins/images/17980/large/photo_2024-09-10_17.09.00.jpeg?1725963446",
    "current_price": 1.82,
    "market_cap": 4921462334,
    "market_cap_rank": 23,
    "fully_diluted_valuation": 9449350221,
    "total_volume": 207530754,
    "high_24h": 1.91,
    "low_24h": 1.77,
    "price_change_24h": -0.07296261215280242,
    "price_change_percentage_24h": -3.85116,
    "market_cap_change_24h": -195195132.74507523,
    "market_cap_change_percentage_24h": -3.8149,
    "circulating_supply": 2701722697.99757,
    "total_supply": 5187385829.506564,
    "max_supply": null,
    "ath": 8.25,
    "ath_change_percentage": -78.12721,
    "ath_date": "2024-06-15T00:36:51.509Z",
    "atl": 0.519364,
    "atl_change_percentage": 247.59728,
    "atl_date": "2021-09-21T00:33:11.092Z",
    "roi": null,
    "last_updated": "2026-05-28T09:15:44.096Z",
    "price_change_percentage_24h_in_currency": -3.8511554515198507
  }
]